{
  "table_of_contents": [],
  "modules": [
    {
      "module_number": 1,
      "title": "",
      "content": [],
      "quiz_questions": []
    },
    {
      "module_number": 2,
      "title": "",
      "content": [],
      "quiz_questions": []
    },
    {
      "module_number": 3,
      "title": "",
      "content": [],
      "quiz_questions": []
    },
    {
      "module_number": 4,
      "title": "",
      "status": "coming_soon",
      "outline": []
    },
    {
      "module_number": 5,
      "title": "",
      "status": "coming_soon",
      "outline": []
    },
    {
      "module_number": 6,
      "title": "",
      "status": "coming_soon",
      "outline": []
    }
  ]
}